mintospy/__init__.py
mintospy/api.py
mintospy/constants.py
mintospy/endpoints.py
mintospy/exceptions.py
mintospy/utils.py
mintospy-0.6.4.dist-info/LICENSE.md
mintospy-0.6.4.dist-info/METADATA
mintospy-0.6.4.dist-info/WHEEL
mintospy-0.6.4.dist-info/top_level.txt
mintospy-0.6.4.dist-info/RECORD
