Metadata-Version: 2.1
Name: mintospy
Version: 0.6.4
Home-page: https://github.com/thicccat688/mintospy
Download-URL: https://pypi.org/project/mintospy
Author: Tomás Perestrelo
Author-email: tomasperestrelo21@gmail.com
License: MIT
Keywords: python,api,api-wrapper,mintos
License-File: LICENSE.md
Requires-Dist: selenium-recaptcha-solver
Requires-Dist: selenium-stealth
Requires-Dist: selenium
Requires-Dist: cloudscraper
Requires-Dist: pandas
Requires-Dist: pyotp
Requires-Dist: bs4
